ppt2video/__init__.py
ppt2video/tools.py
ppt2video-0.1.15.dist-info/LICENSE
ppt2video-0.1.15.dist-info/METADATA
ppt2video-0.1.15.dist-info/WHEEL
ppt2video-0.1.15.dist-info/top_level.txt
ppt2video-0.1.15.dist-info/RECORD
