Metadata-Version: 2.1
Name: ppt2video
Version: 0.1.15
Summary: A tool to convert a PowerPoint (PPT or PPTX) to a video with voice that reads the notes for each slide.
Author-email: IssueTracker <issuetree.tracker@gmail.com>
License: MIT License
Project-URL: Homepage, https://github.com/iburn78/ppt2video
Classifier: Programming Language :: Python :: 3
Classifier: License :: OSI Approved :: MIT License
Classifier: Operating System :: OS Independent
Requires-Python: >=3.6
License-File: LICENSE
Requires-Dist: python-pptx
Requires-Dist: moviepy
Requires-Dist: google-cloud-texttospeech
